et/__init__.py
et/et.py
etime-0.2.dist-info/LICENSE
etime-0.2.dist-info/METADATA
etime-0.2.dist-info/WHEEL
etime-0.2.dist-info/top_level.txt
etime-0.2.dist-info/RECORD
