Metadata-Version: 2.1
Name: etime
Version: 0.2
Summary: A simple package to calculate the execution time of certain lines of code
Home-page: https://github.com/amaljithkuttamath/exectime
Author: Amaljith kuttamath
Author-email: kuttamath.amaljith@gmail.com
License: UNKNOWN
Download-URL: https://github.com/amaljithkuttamath/exectime/archive/0.2.tar.gz
Platform: UNKNOWN
Classifier: Programming Language :: Python :: 3
Classifier: License :: OSI Approved :: MIT License
Classifier: Operating System :: OS Independent
Requires-Python: >=3.6
